JPhoto/Classify.py
JPhoto/Photo.py
JPhoto/__init__.py
JPhotoWorks-0.9.dist-info/DESCRIPTION.rst
JPhotoWorks-0.9.dist-info/METADATA
JPhotoWorks-0.9.dist-info/RECORD
JPhotoWorks-0.9.dist-info/WHEEL
JPhotoWorks-0.9.dist-info/metadata.json
JPhotoWorks-0.9.dist-info/top_level.txt
JUtil/Util.py
JUtil/__init__.py
