Metadata-Version: 2.0
Name: JPhotoWorks
Version: 0.9
Summary: UNKNOWN
Home-page: https://github.com/jjeaby/JPhotoWorks
Author: Lee Yong Jin
Author-email: jjeaby@gmail.com
License: Apache 2.0
Platform: UNKNOWN
Classifier: Programming Language :: Python :: 3
Classifier: Programming Language :: Python :: 3.2
Classifier: Programming Language :: Python :: 3.3
Classifier: Programming Language :: Python :: 3.4
Classifier: Programming Language :: Python :: 3.5
Classifier: Programming Language :: Python :: 3.6
Requires-Dist: piexif
Requires-Dist: pillow
